chat_assistant/__init__.py
chat_assistant-0.2.0.dist-info/licenses/LICENSE
chat_assistant-0.2.0.dist-info/METADATA
chat_assistant-0.2.0.dist-info/WHEEL
chat_assistant-0.2.0.dist-info/top_level.txt
chat_assistant-0.2.0.dist-info/RECORD
