Metadata-Version: 2.4
Name: chat-assistant
Version: 0.2.0
Summary: Chat Assistant
Home-page: https://github.com/sugarkwork/chat_assistant
Author: sugarkwork
License: MIT
Project-URL: Source, https://github.com/sugarkwork/chat_assistant
Classifier: Programming Language :: Python :: 3
Classifier: License :: OSI Approved :: MIT License
Classifier: Operating System :: OS Independent
Classifier: Development Status :: 3 - Alpha
Classifier: Intended Audience :: Developers
Classifier: Topic :: Software Development :: Libraries :: Application Frameworks
Requires-Python: >=3.10
License-File: LICENSE
Requires-Dist: skpmem>=0.2.0
Requires-Dist: litellm
Requires-Dist: json_repair
Dynamic: author
Dynamic: classifier
Dynamic: description
Dynamic: description-content-type
Dynamic: home-page
Dynamic: license
Dynamic: license-file
Dynamic: project-url
Dynamic: requires-dist
Dynamic: requires-python
Dynamic: summary
